<core:FragmentDefinition xmlns="sap.m" xmlns:core="sap.ui.core" xmlns:f="sap.ui.layout.form">
    <Dialog title="Multi-Update Items" contentWidth="500px">
        <content>
            <f:SimpleForm title="Orders" layout="GridLayout">
                <Label text="ID" />
                <Input id="idOrderID4Update1" placeholder="Enter Order ID" width="300px" type="Number" editable="false" liveChange="onIDMultiLiveChange" />

                <Label text="Customer Name" />
                <Input id="idCustomerName1Update1" placeholder="Enter Customer Name" width="300px" editable="true" />

                <!-- <Label text="Order Date" />
                <Input id="idOrderDate1Update1" value="dd-MM-yyyy" placeholder="Enter Order Date" width="300px" editable="false" /> -->
            </f:SimpleForm>
            <!-- <Table id="idMultiUpdateTable" items="{/}">
             <headerToolbar>
					<Toolbar>
						<Title text=" Order Items "/>
						
						
					</Toolbar>
				</headerToolbar>
                <columns>
                    <Column>
                        <Text text="ItemID" />
                    </Column>
                    <Column>
                        <Text text="Product Name" />
                    </Column>
                    <Column>
                        <Text text="Quantity" />
                    </Column>
                    <Column>
                        <Text text="Price" />
                    </Column>
                   
                </columns>
                <items>
                    <ColumnListItem>
                        <cells>
                            <Input value="{ItemID}" id="idItemIDInput1" editable="false" />
                            <Input value="{ProductName}" id="idProductNameInput1" />
                            <Input value="{Quantity}" id="idQuantityInput1" type="Number" />
                            <Input value="{Price}" id="idPriceInput" type="Number" />
                           
                        </cells>
                    </ColumnListItem>
                </items>
            </Table> -->
        </content>
        <beginButton>
            <Button text="Submit" type="Emphasized" press="onUpdateSubmit" />
        </beginButton>
        <endButton>
            <Button text="Close" type="Reject" press="onMultiUpdateClose" />
        </endButton>
    </Dialog>
</core:FragmentDefinition>
